nonebot_plugin_immortal/__init__.py
nonebot_plugin_immortal/config.py
nonebot_plugin_immortal/storage.py
nonebot_plugin_immortal/util.py
nonebot_plugin_immortal/matchers/__init__.py
nonebot_plugin_immortal/matchers/account.py
nonebot_plugin_immortal-0.0.6.dist-info/METADATA
nonebot_plugin_immortal-0.0.6.dist-info/WHEEL
nonebot_plugin_immortal-0.0.6.dist-info/top_level.txt
nonebot_plugin_immortal-0.0.6.dist-info/RECORD
