Metadata-Version: 2.4
Name: nonebot-plugin-immortal
Version: 0.0.6
Summary: 修仙插件
Author-email: BrokenC1oud <jgbsxx20130315@gmail.com>
Requires-Python: >=3.13
Requires-Dist: nonebot-adapter-onebot>=2.4.6
Requires-Dist: nonebot-plugin-alconna>=0.57.6
Requires-Dist: nonebot-plugin-orm[sqlite]>=0.7.7
Requires-Dist: nonebot2>=2.4.2
